pyoo.py
pyoo-1.4.dist-info/LICENSE
pyoo-1.4.dist-info/METADATA
pyoo-1.4.dist-info/WHEEL
pyoo-1.4.dist-info/top_level.txt
pyoo-1.4.dist-info/RECORD
