Metadata-Version: 2.1
Name: pyoo
Version: 1.4
Summary: Pythonic interface to Apache OpenOffice API (UNO)
Home-page: https://github.com/mila/pyoo
Author: Miloslav Pojman
Author-email: miloslav.pojman@gmail.com
License: UNKNOWN
Platform: UNKNOWN
Classifier: Intended Audience :: Developers
Classifier: License :: OSI Approved :: MIT License
Classifier: Programming Language :: Python
Classifier: Topic :: Office/Business :: Office Suites
Classifier: Topic :: Office/Business :: Financial :: Spreadsheet
